fingerprint/__init__.py
fingerprint/fingerprint.py
finger_print-0.1.2.dist-info/LICENSE.txt
finger_print-0.1.2.dist-info/METADATA
finger_print-0.1.2.dist-info/WHEEL
finger_print-0.1.2.dist-info/top_level.txt
finger_print-0.1.2.dist-info/RECORD
